{"directed": true, "multigraph": false, "graph": {}, "nodes": [{"size": 2, "id": " \"http://givingsense.eu/sembib/onto/tpt/biblio/12239\" "}, {"size": 2, "id": " \"http://givingsense.eu/sembib/onto/tpt/biblio/12238\" "}, {"size": 3, "id": " \"http://givingsense.eu/sembib/onto/channels/electromagnetics\" "}, {"size": 4, "id": " \"http://givingsense.eu/sembib/onto/channels/ELECTROMAGNETICS2012\" "}, {"size": 1, "id": " \"electromagnetics\" "}, {"size": 5, "id": " \"http://givingsense.eu/sembib/onto/ELECTROMAGNETICS2012\" "}, {"size": 2, "id": " \"http://givingsense.eu/sembib/onto/tpt/biblio/12479\" "}, {"size": 2, "id": " \"http://givingsense.eu/sembib/onto/tpt/biblio/12730\" "}, {"size": 2, "id": " \"http://givingsense.eu/sembib/onto/ELECTROMAGNETICS2014\" "}, {"size": 1, "id": " \"http://givingsense.eu/sembib/onto/channels/ELECTROMAGNETICS2014\" "}, {"size": 2, "id": " \"http://givingsense.eu/sembib/onto/tpt/biblio/14933\" "}], "links": [{"attr_dict": {"label": " \"http://givingsense.eu/sembib/onto/inConf\" "}, "source": " \"http://givingsense.eu/sembib/onto/tpt/biblio/12239\" ", "target": " \"http://givingsense.eu/sembib/onto/channels/ELECTROMAGNETICS2012\" "}, {"attr_dict": {"label": " \"http://givingsense.eu/sembib/onto/inConf\" "}, "source": " \"http://givingsense.eu/sembib/onto/tpt/biblio/12239\" ", "target": " \"http://givingsense.eu/sembib/onto/ELECTROMAGNETICS2012\" "}, {"attr_dict": {"label": " \"http://givingsense.eu/sembib/onto/inConf\" "}, "source": " \"http://givingsense.eu/sembib/onto/tpt/biblio/12238\" ", "target": " \"http://givingsense.eu/sembib/onto/channels/ELECTROMAGNETICS2012\" "}, {"attr_dict": {"label": " \"http://givingsense.eu/sembib/onto/inConf\" "}, "source": " \"http://givingsense.eu/sembib/onto/tpt/biblio/12238\" ", "target": " \"http://givingsense.eu/sembib/onto/ELECTROMAGNETICS2012\" "}, {"attr_dict": {"label": " \"http://purl.org/dc/elements/1.1/label\" "}, "source": " \"http://givingsense.eu/sembib/onto/channels/electromagnetics\" ", "target": " \"electromagnetics\" "}, {"attr_dict": {"label": " \"http://lod.springer.com/data/ontology/property/hasSeries\" "}, "source": " \"http://givingsense.eu/sembib/onto/ELECTROMAGNETICS2012\" ", "target": " \"http://givingsense.eu/sembib/onto/channels/electromagnetics\" "}, {"attr_dict": {"label": " \"http://givingsense.eu/sembib/onto/inConf\" "}, "source": " \"http://givingsense.eu/sembib/onto/tpt/biblio/12479\" ", "target": " \"http://givingsense.eu/sembib/onto/channels/ELECTROMAGNETICS2012\" "}, {"attr_dict": {"label": " \"http://givingsense.eu/sembib/onto/inConf\" "}, "source": " \"http://givingsense.eu/sembib/onto/tpt/biblio/12479\" ", "target": " \"http://givingsense.eu/sembib/onto/ELECTROMAGNETICS2012\" "}, {"attr_dict": {"label": " \"http://givingsense.eu/sembib/onto/inConf\" "}, "source": " \"http://givingsense.eu/sembib/onto/tpt/biblio/12730\" ", "target": " \"http://givingsense.eu/sembib/onto/channels/ELECTROMAGNETICS2012\" "}, {"attr_dict": {"label": " \"http://givingsense.eu/sembib/onto/inConf\" "}, "source": " \"http://givingsense.eu/sembib/onto/tpt/biblio/12730\" ", "target": " \"http://givingsense.eu/sembib/onto/ELECTROMAGNETICS2012\" "}, {"attr_dict": {"label": " \"http://lod.springer.com/data/ontology/property/hasSeries\" "}, "source": " \"http://givingsense.eu/sembib/onto/ELECTROMAGNETICS2014\" ", "target": " \"http://givingsense.eu/sembib/onto/channels/electromagnetics\" "}, {"attr_dict": {"label": " \"http://givingsense.eu/sembib/onto/inConf\" "}, "source": " \"http://givingsense.eu/sembib/onto/tpt/biblio/14933\" ", "target": " \"http://givingsense.eu/sembib/onto/channels/ELECTROMAGNETICS2014\" "}, {"attr_dict": {"label": " \"http://givingsense.eu/sembib/onto/inConf\" "}, "source": " \"http://givingsense.eu/sembib/onto/tpt/biblio/14933\" ", "target": " \"http://givingsense.eu/sembib/onto/ELECTROMAGNETICS2014\" "}]}