{"directed": true, "multigraph": false, "graph": {}, "nodes": [{"size": 2, "id": " \"http://givingsense.eu/sembib/onto/tpt/biblio/14910\" "}, {"size": 1, "id": " \"http://givingsense.eu/sembib/onto/channels/SIGSPATIAL2015\" "}, {"size": 2, "id": " \"http://givingsense.eu/sembib/onto/SIGSPATIAL2014\" "}, {"size": 1, "id": " \"sigspatial\" "}, {"size": 2, "id": " \"http://givingsense.eu/sembib/onto/tpt/biblio/16005\" "}, {"size": 3, "id": " \"http://givingsense.eu/sembib/onto/channels/sigspatial\" "}, {"size": 1, "id": " \"http://givingsense.eu/sembib/onto/channels/SIGSPATIAL2014\" "}, {"size": 2, "id": " \"http://givingsense.eu/sembib/onto/SIGSPATIAL2015\" "}], "links": [{"attr_dict": {"label": " \"http://givingsense.eu/sembib/onto/inConf\" "}, "source": " \"http://givingsense.eu/sembib/onto/tpt/biblio/14910\" ", "target": " \"http://givingsense.eu/sembib/onto/channels/SIGSPATIAL2014\" "}, {"attr_dict": {"label": " \"http://givingsense.eu/sembib/onto/inConf\" "}, "source": " \"http://givingsense.eu/sembib/onto/tpt/biblio/14910\" ", "target": " \"http://givingsense.eu/sembib/onto/SIGSPATIAL2014\" "}, {"attr_dict": {"label": " \"http://lod.springer.com/data/ontology/property/hasSeries\" "}, "source": " \"http://givingsense.eu/sembib/onto/SIGSPATIAL2014\" ", "target": " \"http://givingsense.eu/sembib/onto/channels/sigspatial\" "}, {"attr_dict": {"label": " \"http://givingsense.eu/sembib/onto/inConf\" "}, "source": " \"http://givingsense.eu/sembib/onto/tpt/biblio/16005\" ", "target": " \"http://givingsense.eu/sembib/onto/channels/SIGSPATIAL2015\" "}, {"attr_dict": {"label": " \"http://givingsense.eu/sembib/onto/inConf\" "}, "source": " \"http://givingsense.eu/sembib/onto/tpt/biblio/16005\" ", "target": " \"http://givingsense.eu/sembib/onto/SIGSPATIAL2015\" "}, {"attr_dict": {"label": " \"http://purl.org/dc/elements/1.1/label\" "}, "source": " \"http://givingsense.eu/sembib/onto/channels/sigspatial\" ", "target": " \"sigspatial\" "}, {"attr_dict": {"label": " \"http://lod.springer.com/data/ontology/property/hasSeries\" "}, "source": " \"http://givingsense.eu/sembib/onto/SIGSPATIAL2015\" ", "target": " \"http://givingsense.eu/sembib/onto/channels/sigspatial\" "}]}