{"directed": true, "multigraph": false, "graph": {}, "nodes": [{"size": 1, "id": " \"paris\" "}, {"size": 2, "id": " \"http://givingsense.eu/sembib/onto/PARIS2013\" "}, {"size": 1, "id": " \"http://givingsense.eu/sembib/onto/channels/PARIS2013\" "}, {"size": 2, "id": " \"http://givingsense.eu/sembib/onto/tpt/biblio/15777\" "}, {"size": 2, "id": " \"http://givingsense.eu/sembib/onto/PARIS2015\" "}, {"size": 1, "id": " \"http://givingsense.eu/sembib/onto/channels/PARIS2015\" "}, {"size": 3, "id": " \"http://givingsense.eu/sembib/onto/channels/paris\" "}, {"size": 2, "id": " \"http://givingsense.eu/sembib/onto/tpt/biblio/13972\" "}], "links": [{"attr_dict": {"label": " \"http://lod.springer.com/data/ontology/property/hasSeries\" "}, "source": " \"http://givingsense.eu/sembib/onto/PARIS2013\" ", "target": " \"http://givingsense.eu/sembib/onto/channels/paris\" "}, {"attr_dict": {"label": " \"http://givingsense.eu/sembib/onto/inConf\" "}, "source": " \"http://givingsense.eu/sembib/onto/tpt/biblio/15777\" ", "target": " \"http://givingsense.eu/sembib/onto/channels/PARIS2015\" "}, {"attr_dict": {"label": " \"http://givingsense.eu/sembib/onto/inConf\" "}, "source": " \"http://givingsense.eu/sembib/onto/tpt/biblio/15777\" ", "target": " \"http://givingsense.eu/sembib/onto/PARIS2015\" "}, {"attr_dict": {"label": " \"http://lod.springer.com/data/ontology/property/hasSeries\" "}, "source": " \"http://givingsense.eu/sembib/onto/PARIS2015\" ", "target": " \"http://givingsense.eu/sembib/onto/channels/paris\" "}, {"attr_dict": {"label": " \"http://purl.org/dc/elements/1.1/label\" "}, "source": " \"http://givingsense.eu/sembib/onto/channels/paris\" ", "target": " \"paris\" "}, {"attr_dict": {"label": " \"http://givingsense.eu/sembib/onto/inConf\" "}, "source": " \"http://givingsense.eu/sembib/onto/tpt/biblio/13972\" ", "target": " \"http://givingsense.eu/sembib/onto/channels/PARIS2013\" "}, {"attr_dict": {"label": " \"http://givingsense.eu/sembib/onto/inConf\" "}, "source": " \"http://givingsense.eu/sembib/onto/tpt/biblio/13972\" ", "target": " \"http://givingsense.eu/sembib/onto/PARIS2013\" "}]}