{"directed": true, "multigraph": false, "graph": {}, "nodes": [{"size": 2, "id": " \"http://givingsense.eu/sembib/onto/channels/VLDB2014\" "}, {"size": 1, "id": " \"http://givingsense.eu/sembib/onto/channels/VLDB2013\" "}, {"size": 2, "id": " \"http://givingsense.eu/sembib/onto/VLDB2013\" "}, {"size": 2, "id": " \"http://givingsense.eu/sembib/onto/tpt/biblio/15042\" "}, {"size": 2, "id": " \"http://givingsense.eu/sembib/onto/tpt/biblio/15045\" "}, {"size": 2, "id": " \"http://givingsense.eu/sembib/onto/tpt/biblio/13951\" "}, {"size": 3, "id": " \"http://givingsense.eu/sembib/onto/VLDB2014\" "}, {"size": 3, "id": " \"http://givingsense.eu/sembib/onto/channels/vldb\" "}, {"size": 1, "id": " \"vldb\" "}], "links": [{"attr_dict": {"label": " \"http://lod.springer.com/data/ontology/property/hasSeries\" "}, "source": " \"http://givingsense.eu/sembib/onto/VLDB2013\" ", "target": " \"http://givingsense.eu/sembib/onto/channels/vldb\" "}, {"attr_dict": {"label": " \"http://givingsense.eu/sembib/onto/inConf\" "}, "source": " \"http://givingsense.eu/sembib/onto/tpt/biblio/15042\" ", "target": " \"http://givingsense.eu/sembib/onto/channels/VLDB2014\" "}, {"attr_dict": {"label": " \"http://givingsense.eu/sembib/onto/inConf\" "}, "source": " \"http://givingsense.eu/sembib/onto/tpt/biblio/15042\" ", "target": " \"http://givingsense.eu/sembib/onto/VLDB2014\" "}, {"attr_dict": {"label": " \"http://givingsense.eu/sembib/onto/inConf\" "}, "source": " \"http://givingsense.eu/sembib/onto/tpt/biblio/15045\" ", "target": " \"http://givingsense.eu/sembib/onto/channels/VLDB2014\" "}, {"attr_dict": {"label": " \"http://givingsense.eu/sembib/onto/inConf\" "}, "source": " \"http://givingsense.eu/sembib/onto/tpt/biblio/15045\" ", "target": " \"http://givingsense.eu/sembib/onto/VLDB2014\" "}, {"attr_dict": {"label": " \"http://givingsense.eu/sembib/onto/inConf\" "}, "source": " \"http://givingsense.eu/sembib/onto/tpt/biblio/13951\" ", "target": " \"http://givingsense.eu/sembib/onto/channels/VLDB2013\" "}, {"attr_dict": {"label": " \"http://givingsense.eu/sembib/onto/inConf\" "}, "source": " \"http://givingsense.eu/sembib/onto/tpt/biblio/13951\" ", "target": " \"http://givingsense.eu/sembib/onto/VLDB2013\" "}, {"attr_dict": {"label": " \"http://lod.springer.com/data/ontology/property/hasSeries\" "}, "source": " \"http://givingsense.eu/sembib/onto/VLDB2014\" ", "target": " \"http://givingsense.eu/sembib/onto/channels/vldb\" "}, {"attr_dict": {"label": " \"http://purl.org/dc/elements/1.1/label\" "}, "source": " \"http://givingsense.eu/sembib/onto/channels/vldb\" ", "target": " \"vldb\" "}]}