{"directed": true, "multigraph": false, "graph": {}, "nodes": [{"size": 2, "id": " \"http://givingsense.eu/sembib/onto/channels/mid\" "}, {"size": 1, "id": " \"http://givingsense.eu/sembib/onto/channels/MID2014\" "}, {"size": 1, "id": " \"mid\" "}, {"size": 2, "id": " \"http://givingsense.eu/sembib/onto/tpt/biblio/15657\" "}, {"size": 2, "id": " \"http://givingsense.eu/sembib/onto/MID2014\" "}], "links": [{"attr_dict": {"label": " \"http://purl.org/dc/elements/1.1/label\" "}, "source": " \"http://givingsense.eu/sembib/onto/channels/mid\" ", "target": " \"mid\" "}, {"attr_dict": {"label": " \"http://givingsense.eu/sembib/onto/inConf\" "}, "source": " \"http://givingsense.eu/sembib/onto/tpt/biblio/15657\" ", "target": " \"http://givingsense.eu/sembib/onto/channels/MID2014\" "}, {"attr_dict": {"label": " \"http://givingsense.eu/sembib/onto/inConf\" "}, "source": " \"http://givingsense.eu/sembib/onto/tpt/biblio/15657\" ", "target": " \"http://givingsense.eu/sembib/onto/MID2014\" "}, {"attr_dict": {"label": " \"http://lod.springer.com/data/ontology/property/hasSeries\" "}, "source": " \"http://givingsense.eu/sembib/onto/MID2014\" ", "target": " \"http://givingsense.eu/sembib/onto/channels/mid\" "}]}