{"directed": true, "multigraph": false, "graph": {}, "nodes": [{"size": 2, "id": " \"http://givingsense.eu/sembib/onto/tpt/biblio/11204\" "}, {"size": 3, "id": " \"http://givingsense.eu/sembib/onto/channels/notere\" "}, {"size": 1, "id": " \"http://givingsense.eu/sembib/onto/channels/NOTERE2012\" "}, {"size": 2, "id": " \"http://givingsense.eu/sembib/onto/tpt/biblio/11403\" "}, {"size": 3, "id": " \"http://givingsense.eu/sembib/onto/NOTERE2011\" "}, {"size": 2, "id": " \"http://givingsense.eu/sembib/onto/tpt/biblio/12880\" "}, {"size": 2, "id": " \"http://givingsense.eu/sembib/onto/channels/NOTERE2011\" "}, {"size": 2, "id": " \"http://givingsense.eu/sembib/onto/NOTERE2012\" "}, {"size": 1, "id": " \"notere\" "}], "links": [{"attr_dict": {"label": " \"http://givingsense.eu/sembib/onto/inConf\" "}, "source": " \"http://givingsense.eu/sembib/onto/tpt/biblio/11204\" ", "target": " \"http://givingsense.eu/sembib/onto/channels/NOTERE2011\" "}, {"attr_dict": {"label": " \"http://givingsense.eu/sembib/onto/inConf\" "}, "source": " \"http://givingsense.eu/sembib/onto/tpt/biblio/11204\" ", "target": " \"http://givingsense.eu/sembib/onto/NOTERE2011\" "}, {"attr_dict": {"label": " \"http://purl.org/dc/elements/1.1/label\" "}, "source": " \"http://givingsense.eu/sembib/onto/channels/notere\" ", "target": " \"notere\" "}, {"attr_dict": {"label": " \"http://givingsense.eu/sembib/onto/inConf\" "}, "source": " \"http://givingsense.eu/sembib/onto/tpt/biblio/11403\" ", "target": " \"http://givingsense.eu/sembib/onto/channels/NOTERE2011\" "}, {"attr_dict": {"label": " \"http://givingsense.eu/sembib/onto/inConf\" "}, "source": " \"http://givingsense.eu/sembib/onto/tpt/biblio/11403\" ", "target": " \"http://givingsense.eu/sembib/onto/NOTERE2011\" "}, {"attr_dict": {"label": " \"http://lod.springer.com/data/ontology/property/hasSeries\" "}, "source": " \"http://givingsense.eu/sembib/onto/NOTERE2011\" ", "target": " \"http://givingsense.eu/sembib/onto/channels/notere\" "}, {"attr_dict": {"label": " \"http://givingsense.eu/sembib/onto/inConf\" "}, "source": " \"http://givingsense.eu/sembib/onto/tpt/biblio/12880\" ", "target": " \"http://givingsense.eu/sembib/onto/channels/NOTERE2012\" "}, {"attr_dict": {"label": " \"http://givingsense.eu/sembib/onto/inConf\" "}, "source": " \"http://givingsense.eu/sembib/onto/tpt/biblio/12880\" ", "target": " \"http://givingsense.eu/sembib/onto/NOTERE2012\" "}, {"attr_dict": {"label": " \"http://lod.springer.com/data/ontology/property/hasSeries\" "}, "source": " \"http://givingsense.eu/sembib/onto/NOTERE2012\" ", "target": " \"http://givingsense.eu/sembib/onto/channels/notere\" "}]}