{"directed": true, "multigraph": false, "graph": {}, "nodes": [{"size": 2, "id": " \"http://givingsense.eu/sembib/onto/CEWQO2014\" "}, {"size": 2, "id": " \"http://givingsense.eu/sembib/onto/channels/cewqo\" "}, {"size": 1, "id": " \"http://givingsense.eu/sembib/onto/channels/CEWQO2014\" "}, {"size": 1, "id": " \"cewqo\" "}, {"size": 2, "id": " \"http://givingsense.eu/sembib/onto/tpt/biblio/14676\" "}], "links": [{"attr_dict": {"label": " \"http://lod.springer.com/data/ontology/property/hasSeries\" "}, "source": " \"http://givingsense.eu/sembib/onto/CEWQO2014\" ", "target": " \"http://givingsense.eu/sembib/onto/channels/cewqo\" "}, {"attr_dict": {"label": " \"http://purl.org/dc/elements/1.1/label\" "}, "source": " \"http://givingsense.eu/sembib/onto/channels/cewqo\" ", "target": " \"cewqo\" "}, {"attr_dict": {"label": " \"http://givingsense.eu/sembib/onto/inConf\" "}, "source": " \"http://givingsense.eu/sembib/onto/tpt/biblio/14676\" ", "target": " \"http://givingsense.eu/sembib/onto/channels/CEWQO2014\" "}, {"attr_dict": {"label": " \"http://givingsense.eu/sembib/onto/inConf\" "}, "source": " \"http://givingsense.eu/sembib/onto/tpt/biblio/14676\" ", "target": " \"http://givingsense.eu/sembib/onto/CEWQO2014\" "}]}